__init__.py
pygame_ui_controls.py
pygame_ui_controls-1.1.3.dist-info/LICENSE
pygame_ui_controls-1.1.3.dist-info/METADATA
pygame_ui_controls-1.1.3.dist-info/WHEEL
pygame_ui_controls-1.1.3.dist-info/top_level.txt
pygame_ui_controls-1.1.3.dist-info/RECORD
